README.rst
setup.py
aio_anticaptcha/__init__.py
aio_anticaptcha.egg-info/PKG-INFO
aio_anticaptcha.egg-info/SOURCES.txt
aio_anticaptcha.egg-info/dependency_links.txt
aio_anticaptcha.egg-info/requires.txt
aio_anticaptcha.egg-info/top_level.txt