Metadata-Version: 1.0
Name: aio-anticaptcha
Version: 0.1.0
Summary: Real-time captcha-to-text decodings
Home-page: https://github.com/nibrag/aio_anticaptcha
Author: Nail Ibragimov
Author-email: ibragwork@gmail.com
License: Apache 2
Keywords: antigate captcha anticaptcha
Platform: UNKNOWN
